odeintw/__init__.py
odeintw/_odeintw.py
odeintw/tests/__init__.py
odeintw/tests/test_odeintw.py
ulysses/BHProp.py
ulysses/__init__.py
ulysses/etab1BE1F.py
ulysses/etab1BE1F_Case2.py
ulysses/etab1BE1F_Case3.py
ulysses/etab1BE1F_Case4.py
ulysses/etab1BE1F_tester.py
ulysses/etab1BE1Fscalefactor_gstar.txt
ulysses/etab1BE1Fscalefactor_gstarS.txt
ulysses/etab1BE1Fsf.py
ulysses/etab1BE2F.py
ulysses/etab1BE3F.py
ulysses/etab1DME.py
ulysses/etab2BE1F.py
ulysses/etab2BE2F.py
ulysses/etab2BE3F.py
ulysses/etab2DME.py
ulysses/etab2RES.py
ulysses/etab2RESmix.py
ulysses/etab2RESsp.py
ulysses/etab3DME.py
ulysses/etab3DMEsct.py
ulysses/etabARS.py
ulysses/etabARS_09Nov.py
ulysses/etabARS_09Nov_v2.py
ulysses/etabARS_new_v4.py
ulysses/etabARS_new_v5.py
ulysses/etabARS_new_v6.py
ulysses/etabARS_test.py
ulysses/etabARS_ul.py
ulysses/etabPBH.py
ulysses/etabPBH_vf.py
ulysses/numba.py
ulysses/timedil.txt
ulysses/tools.py
ulysses/ulsbase.py
ulysses/data/Log_M.txt
ulysses/data/Log_z.txt
ulysses/data/g0log.dat
ulysses/data/g1log.dat
ulysses/data/g2log.dat
ulysses/data/s0log_massdep.txt
ulysses/data/s1log_massdep.txt
ulysses/data/s2log_massdep.txt
ulysses-2.0.11.data/scripts/uls-calc
ulysses-2.0.11.data/scripts/uls-models
ulysses-2.0.11.data/scripts/uls-nest
ulysses-2.0.11.data/scripts/uls-scan
ulysses-2.0.11.data/scripts/uls-scan2D
ulysses-2.0.11.dist-info/LICENSE
ulysses-2.0.11.dist-info/METADATA
ulysses-2.0.11.dist-info/WHEEL
ulysses-2.0.11.dist-info/top_level.txt
ulysses-2.0.11.dist-info/RECORD
