Metadata-Version: 2.1
Name: ulysses
Version: 2.0.11
Summary: ULYSSES: Universal LeptogeneSiS Equation Solver
Home-page: https://github.com/earlyuniverse/ulysses
Author: Alessandro Granelli, Christopher Leslie, Yuber Perez Gonzalez, Brian Shuve,  Holger Schulz, Jessica Turner, Rosie Walker
Author-email: jessicaturner.5390@gmail.com
Requires-Python: >3.6.0
License-File: LICENSE
Requires-Dist: numpy
Requires-Dist: scipy
Requires-Dist: matplotlib
Requires-Dist: pymultinest
Requires-Dist: progressbar
Requires-Dist: python-dateutil
Requires-Dist: termcolor
Requires-Dist: tqdm
